<?xml version='1.0' encoding='utf-8'?>
<!DOCTYPE hibernate-configuration PUBLIC
    "-//Hibernate/Hibernate Configuration DTD//EN"
    "http://www.hibernate.org/dtd/hibernate-configuration-3.0.dtd">
<hibernate-configuration>
  <session-factory>
    <property name="connection.url">jdbc:mysql://localhost:3306</property>
    <property name="connection.driver_class">com.mysql.jdbc.Driver</property>
      <mapping class="bootTest.pojo.BookEntity"/>
      <mapping resource="bootTest/pojo/BookEntity.hbm.xml"/>
      <mapping class="bootTest.pojo.BooktypeEntity"/>
      <mapping resource="bootTest/pojo/BooktypeEntity.hbm.xml"/>
      <mapping class="bootTest.pojo.BorrowrecordEntity"/>
      <mapping resource="bootTest/pojo/BorrowrecordEntity.hbm.xml"/>
      <mapping class="bootTest.pojo.LostbookEntity"/>
      <mapping resource="bootTest/pojo/LostbookEntity.hbm.xml"/>
      <mapping class="bootTest.pojo.PermissionEntity"/>
      <mapping resource="bootTest/pojo/PermissionEntity.hbm.xml"/>
      <mapping class="bootTest.pojo.UserEntity"/>
      <mapping resource="bootTest/pojo/UserEntity.hbm.xml"/>
       <property name="connection.username">root</property>
     <property name="connection.password">123456</property>

    <!-- DB schema will be updated if needed -->
    <!-- <property name="hbm2ddl.auto">update</property> -->
  </session-factory>
</hibernate-configuration>